getgfs/__init__.py
getgfs/decode.py
getgfs/getgfs.py
getgfs/test.py
gfspy/__init__.py
gfspy/decode.py
gfspy/gfspy.py
gfspy/test.py
getgfs-1.2.0.dist-info/LICENSE
getgfs-1.2.0.dist-info/METADATA
getgfs-1.2.0.dist-info/WHEEL
getgfs-1.2.0.dist-info/top_level.txt
getgfs-1.2.0.dist-info/RECORD
