Metadata-Version: 2.1
Name: getgfs
Version: 1.2.0
Summary: getgfs extracts weather forecast variables from the NOAA GFS forecast
Home-page: https://getgfs.readthedocs.io/
Author: Jago Strong-Wright
Author-email: jagoosw@protonmail.com
License: LICENSE.txt
Classifier: Programming Language :: Python :: 3
Classifier: License :: OSI Approved :: GNU General Public License v3 (GPLv3)
Classifier: Operating System :: OS Independent
Classifier: Topic :: Text Processing :: Markup :: Markdown
License-File: LICENSE
Requires-Dist: scipy
Requires-Dist: requests
Requires-Dist: fuzzywuzzy
Requires-Dist: numpy
Requires-Dist: python-dateutil
Requires-Dist: regex
